tox_report/__init__.py
tox_report/hooks.py
tox_report-0.1.0.dist-info/LICENSE
tox_report-0.1.0.dist-info/METADATA
tox_report-0.1.0.dist-info/WHEEL
tox_report-0.1.0.dist-info/entry_points.txt
tox_report-0.1.0.dist-info/top_level.txt
tox_report-0.1.0.dist-info/RECORD
